mwingslite/__init__.py
mwingslite/common.py
mwingslite/parsers/__init__.py
mwingslite/parsers/act.py
mwingslite/parsers/app_aria.py
mwingslite/parsers/app_cue.py
mwingslite/parsers/app_cue_pal_event.py
mwingslite/parsers/app_io.py
mwingslite/parsers/app_pal_amb.py
mwingslite/parsers/app_pal_mot.py
mwingslite/parsers/app_pal_openclose.py
mwingslite/parsers/app_twelite.py
mwingslite/parsers/app_uart_ascii.py
mwingslite/parsers/app_uart_ascii_extended.py
mwingslite/py.typed
mwingslite/serializers/__init__.py
mwingslite/serializers/app_io.py
mwingslite/serializers/app_pal_notice.py
mwingslite/serializers/app_pal_notice_detailed.py
mwingslite/serializers/app_pal_notice_event.py
mwingslite/serializers/app_twelite.py
mwingslite/serializers/app_uart_ascii.py
mwingslite/utils.py
mwingslite-1.0.18.dist-info/LICENSE
mwingslite-1.0.18.dist-info/METADATA
mwingslite-1.0.18.dist-info/WHEEL
mwingslite-1.0.18.dist-info/RECORD
