Metadata-Version: 2.3
Name: mwingslite
Version: 1.0.18
Summary: Communicate with TWELITE wireless modules (Lite edition)
License: MW-OSSLA
Author: Mono Wireless Inc.
Author-email: mono-oss@mono-wireless.com
Requires-Python: >=3.11,<4.0
Classifier: License :: Other/Proprietary License
Classifier: Programming Language :: Python :: 3
Classifier: Programming Language :: Python :: 3.11
Classifier: Programming Language :: Python :: 3.12
Classifier: Programming Language :: Python :: 3.13
Requires-Dist: overrides (>=7.4.0,<8.0.0)
Requires-Dist: pydantic (>=2.5.2,<3.0.0)
Requires-Dist: pyee (>=11.1.0,<12.0.0)
Requires-Dist: pyserial (>=3.5,<4.0)
Project-URL: Documentation, https://monowireless.github.io/mwings_python_lite/index.html
Project-URL: Repository, https://github.com/monowireless/mwings_python_lite
